EPUIKit/__init__.py
EPUIKit/date.py
EPUIKit/epaper.py
EPUIKit/paper.py
EPUIKit/virtualpaper.py
EPUIKit/utils/__init__.py
EPUIKit/utils/dimension.py
EPUIKit/utils/uiloop.py
EPUIKit/utils/uitask.py
EPUIKit/widget/__init__.py
EPUIKit/widget/flowlayout.py
EPUIKit/widget/label.py
EPUIKit/widget/layout.py
EPUIKit/widget/quadrantslayout.py
EPUIKit/widget/widget.py
epuikit-0.0.6.dist-info/METADATA
epuikit-0.0.6.dist-info/WHEEL
epuikit-0.0.6.dist-info/top_level.txt
epuikit-0.0.6.dist-info/RECORD
