Metadata-Version: 2.1
Name: epuikit
Version: 0.0.6
Summary: UIKit for Raspberry on E-Paper
Home-page: https://github.com/jinsihou19/E-Paper-UI-Kit
Author: jinsihou
Author-email: 540097546@qq.com
License: UNKNOWN
Keywords: raspberry epaper uikit
Platform: UNKNOWN
Classifier: Development Status :: 3 - Alpha
Classifier: Intended Audience :: Developers
Classifier: License :: OSI Approved :: MIT License
Classifier: Operating System :: OS Independent
Classifier: Programming Language :: Python :: 3
Requires-Dist: interval
